{"Start": {"starting":true,"connects_to":["XP V","key III","boss IV","stealth III","uncategorized XIII","dangerous areas II"]},
"XP V": {"connects_to":["defy death LIV","healing IV","defy death L","ranged weapon VIII","vitality I","ranged weapon V"],"requires":"|Void:4|"},
"defy death LIV": {"connects_to":["fearless II","vitality V","challenge VI","defy death XXXIII"],"requires":"|Spruce Branch:5| and |Incense:5|"},
"fearless II": {"connects_to":["vitality X","melee weapon X","price V"],"requires":"|Cinders:3|"},
"key III": {"connects_to":["time III","melee weapon II","vitality XIV"],"requires":"|Spruce Branch:8|"},
"time III": {"connects_to":["dangerous areas V","knowledge I","second chance III","defy death I"],"requires":"|Incense:4|"},
"boss IV": {"connects_to":["defy death XX","army V","army I"],"requires":"|Stardust:4|"},
"vitality X": {"connects_to":["XP VI","traps XV","price IV"],"requires":"|Limestone:11|"},
"melee weapon X": {"connects_to":["traps III","travel IV"],"requires":"|Slate:4| and |Strawberry:4|"},
"dangerous areas V": {"connects_to":["defy death XXXVI","speed V","speed VII"],"requires":"|Basalt:4|"},
"defy death XX": {"connects_to":["defy death XIV","defy death XXII","utility II"],"requires":"|Lilypad:5|"},
"melee weapon II": {"connects_to":["knowledge XXXII","defense V","XP XI"],"requires":"|Snow:5|"},
"stealth III": {"connects_to":["stamina I","key II","challenge II"],"requires":"|Clay:4|"},
"XP VI": {"connects_to":["goal I","vitality XIII","goal VIII","goal V"],"requires":"|Iron:4| and |Chalk:4|"},
"healing IV": {"connects_to":["fearless I","speed IV","uncategorized II"],"requires":"|Rabbit Foot:5|"},
"fearless I": {"connects_to":["vitality VIII","goal III","sight III","vitality VII"],"requires":"|Spruce Branch:3|"},
"goal I": {"connects_to":["stealth IV","price XIV"],"requires":"|Iron:4| and |Strawberry:4|"},
"knowledge I": {"connects_to":["challenge VIII","XP XV","knowledge XXIV"],"requires":"|Slate:4|"},
"speed IV": {"connects_to":["knowledge XXIII"],"requires":"|Lilypad:4| and |Rabbit Foot:4|"},
"challenge VIII": {"connects_to":["mana IV"],"requires":"|Snow:12|"},
"traps III": {"connects_to":["sun I","explosion IV","entrance rando I"],"requires":"|Slate:10|"},
"vitality VIII": {"connects_to":["dangerous areas VI","knowledge VI","challenge I"],"requires":"|Stardust:7| and |Slate:7|"},
"goal III": {"connects_to":["macguffins V"],"requires":"|Stardust:4| and |Cinders:4|"},
"sun I": {"connects_to":["defy death XVI","traps VII","dangerous areas III"],"requires":"|Slate:7|"},
"stamina I": {"connects_to":["healing X","starting II"],"requires":"|Iron:4|"},
"sight III": {"connects_to":["refund IV"],"requires":"|Iron:5|"},
"defy death XXXVI": {"connects_to":["careful movement III","knowledge XXXI","knowledge XVIII"],"requires":"|Iron:8|"},
"speed V": {"connects_to":["uncategorized IX","mana III"],"requires":"|Stardust:6| and |Spruce Branch:6|"},
"defy death L": {"connects_to":["utility III","attack V"],"requires":"|Incense:5|"},
"careful movement III": {"connects_to":["boss VI","dangerous areas VIII","mana VI"],"requires":"|Stardust:5| and |Iron:5|"},
"defy death XVI": {"connects_to":["defy death XXXI"],"requires":"|Void:7| and |Rabbit Foot:7|"},
"utility III": {"connects_to":["goal XI","knowledge XI","attack VIII"],"requires":"|Slate:4|"},
"price V": {"connects_to":["knowledge XVI","mana II"],"requires":"|Snow:7|"},
"traps XV": {"connects_to":["XP X","price II"],"requires":"|Iron:10|"},
"knowledge XVI": {"connects_to":["defy death LX","speed III"],"requires":"|Chalk:5|"},
"knowledge XXXII": {"connects_to":["speed I","traps X","knowledge II"],"requires":"|Cinders:3|"},
"dangerous areas VI": {"connects_to":["second chance VI","luck I","link III"],"requires":"|Clay:6|"},
"uncategorized II": {"connects_to":["time II"],"requires":"|Cinders:6| and |Basalt:6|"},
"price IV": {"connects_to":["XP XIV"],"requires":"|Stardust:9|"},
"XP X": {"connects_to":["slots III","uncategorized VI"],"requires":"|Incense:5| and |Void:5|"},
"price II": {"connects_to":["knowledge XII"],"requires":"|Limestone:10|"},
"knowledge VI": {"connects_to":["uncategorized XV"],"requires":"|Basalt:5|"},
"vitality VII": {"requires":"|Spruce Branch:6| and |Lilypad:6|"},
"boss VI": {"connects_to":["challenge VII","macguffins III"],"requires":"|Basalt:4| and |Strawberry:4|"},
"defy death LX": {"connects_to":["boss VII","healing VI","uncategorized XVI"],"requires":"|Snow:4| and |Slate:4|"},
"defy death XIV": {"connects_to":["boss V","god I"],"requires":"|Incense:5|"},
"goal XI": {"connects_to":["price XII","defy death XXXII"],"requires":"|Clay:4| and |Void:4|"},
"stealth IV": {"connects_to":["defy death LVI","refund III","defy death XVII"],"requires":"|Eel:5| and |Limestone:5|"},
"price XII": {"connects_to":["price I","XP III"],"requires":"|Clay:4| and |Cinders:4|"},
"ranged weapon VIII": {"connects_to":["melee weapon VIII","healing IX"],"requires":"|Strawberry:4| and |Snow:4|"},
"macguffins V": {"connects_to":["vitality VI","XP II"],"requires":"|Strawberry:9| and |Spruce Branch:9|"},
"vitality V": {"connects_to":["knowledge X","defense VI","travel III"],"requires":"|Void:9|"},
"army V": {"connects_to":["second chance II","uncategorized XI"],"requires":"|Snow:3|"},
"vitality XIV": {"connects_to":["attack VI","stealth I"],"requires":"|Snow:4| and |Rabbit Foot:4|"},
"defy death LVI": {"connects_to":["goal XIII"],"requires":"|Void:7| and |Iron:7|"},
"challenge VI": {"connects_to":["defy death XXXVII"],"requires":"|Iron:9|"},
"XP XV": {"connects_to":["price III","defy death XXXXII"],"requires":"|Stardust:8|"},
"vitality VI": {"connects_to":["price XVI"],"requires":"|Iron:9| and |Lilypad:9|"},
"knowledge X": {"connects_to":["knowledge XXVIII"],"requires":"|Rabbit Foot:4|"},
"challenge VII": {"connects_to":["boss II","mana I"],"requires":"|Strawberry:9| and |Spruce Branch:9|"},
"second chance II": {"connects_to":["starting I"],"requires":"|Rabbit Foot:5|"},
"knowledge XXVIII": {"connects_to":["vitality XI","healing II","choice IV"],"requires":"|Lilypad:5|"},
"defense VI": {"connects_to":["progression balancing III","stealth II"],"requires":"|Strawberry:5|"},
"boss V": {"connects_to":["traps XI","ranged weapon III","defy death XII"],"requires":"|Strawberry:4| and |Snow:4|"},
"uncategorized XV": {"connects_to":["fire II"],"requires":"|Stardust:10| and |Spruce Branch:10|"},
"boss VII": {"connects_to":["progression balancing IV"],"requires":"|Basalt:4| and |Cinders:4|"},
"refund IV": {"connects_to":["stealth V","defy death XXXXIII"],"requires":"|Spruce Branch:8|"},
"key II": {"requires":"|Eel:5| and |Snow:5|"},
"traps VII": {"connects_to":["dangerous areas XIV","goal X","careful movement IV"],"requires":"|Slate:9| and |Stardust:9|"},
"attack V": {"connects_to":["knowledge XXV","goal II"],"requires":"|Strawberry:4| and |Basalt:4|"},
"price III": {"connects_to":["healing I"],"requires":"|Chalk:5| and |Limestone:5|"},
"traps XI": {"connects_to":["defy death VIII","amnesty III","defy death VI"],"requires":"|Clay:5| and |Lilypad:5|"},
"mana II": {"requires":"|Strawberry:5|"},
"stealth V": {"connects_to":["goal IV","macguffins VII"],"requires":"|Strawberry:4| and |Lilypad:4|"},
"ranged weapon III": {"connects_to":["attack VII"],"requires":"|Incense:7| and |Cinders:7|"},
"melee weapon VIII": {"connects_to":["travel II"],"requires":"|Limestone:4| and |Snow:4|"},
"uncategorized IX": {"connects_to":["slots I"],"requires":"|Lilypad:14|"},
"healing X": {"connects_to":["attack I","second chance VIII","slots IV"],"requires":"|Lilypad:4|"},
"refund III": {"connects_to":["healing VIII","price XI"],"requires":"|Void:7| and |Strawberry:7|"},
"speed I": {"connects_to":["defy death XXXXVI","macguffins I"],"requires":"|Slate:10|"},
"attack VI": {"connects_to":["healing III","defy death XXXIX"],"requires":"|Incense:7|"},
"second chance VI": {"connects_to":["careful movement II","price XV","uncategorized XIV"],"requires":"|Chalk:6|"},
"knowledge XXIII": {"connects_to":["dangerous areas XIII","copy II"],"requires":"|Cinders:5|"},
"travel II": {"connects_to":["ice II","logic II"],"requires":"|Clay:4|"},
"luck I": {"connects_to":["uncategorized X"],"requires":"|Eel:9| and |Rabbit Foot:9|"},
"knowledge XXXI": {"connects_to":["traps XII","careful movement I"],"requires":"|Lilypad:5|"},
"progression balancing IV": {"connects_to":["second chance IV"],"requires":"|Eel:17| and |Limestone:17|"},
"dangerous areas XIV": {"connects_to":["melee weapon IX","defy death XXX"],"requires":"|Rabbit Foot:4| and |Basalt:4|"},
"defy death VIII": {"connects_to":["knowledge VIII","defy death LV"],"requires":"|Strawberry:5| and |Stardust:5|"},
"healing I": {"connects_to":["knowledge XX","vitality XVI"],"requires":"|Iron:7|"},
"speed VII": {"connects_to":["traps XIII"],"requires":"|Stardust:10|"},
"defense V": {"connects_to":["ammo I","defy death XI"],"requires":"|Basalt:4|"},
"god I": {"connects_to":["fragment III","luck II","defense III"],"requires":"|Clay:5|"},
"careful movement II": {"connects_to":["defy death XXVIII","price X","melee weapon VI"],"requires":"|Clay:7| and |Lilypad:7|"},
"dangerous areas XIII": {"connects_to":["knowledge XXVII","vitality XII"],"requires":"|Strawberry:5|"},
"goal XIII": {"connects_to":["knowledge XIII","defy death XIII"],"requires":"|Clay:12|"},
"goal IV": {"connects_to":["uncategorized I","copy III"],"requires":"|Rabbit Foot:9|"},
"uncategorized XI": {"requires":"|Chalk:7| and |Strawberry:7|"},
"knowledge XI": {"connects_to":["knowledge XXI","ice I"],"requires":"|Lilypad:4|"},
"uncategorized I": {"connects_to":["utility V"],"requires":"|Stardust:21|"},
"healing III": {"connects_to":["vitality XV","goal VI"],"requires":"|Limestone:5|"},
"second chance III": {"connects_to":["defy death XXXXVIII"],"requires":"|Incense:5|"},
"defy death XXXXVI": {"connects_to":["uncategorized XIX"],"requires":"|Lilypad:8|"},
"defy death I": {"requires":"|Spruce Branch:10|"},
"ice II": {"connects_to":["defy death XXXX","defy death XXVII"],"requires":"|Iron:4|"},
"boss II": {"connects_to":["defense IV","goal XV","uncategorized XII"],"requires":"|Eel:10|"},
"traps XIII": {"connects_to":["water I"],"requires":"|Snow:10|"},
"traps XII": {"connects_to":["defy death XXXXIV","knowledge XXIX"],"requires":"|Limestone:11|"},
"knowledge XXVII": {"connects_to":["defy death V","price IX","defy death II"],"requires":"|Cinders:6|"},
"vitality XIII": {"connects_to":["enemy damage II"],"requires":"|Clay:8| and |Slate:8|"},
"defy death XXII": {"connects_to":["time V","uncategorized V"],"requires":"|Iron:6|"},
"speed III": {"connects_to":["army III"],"requires":"|Cinders:8| and |Chalk:8|"},
"time V": {"connects_to":["choice I","knowledge XIX"],"requires":"|Snow:4| and |Limestone:4|"},
"price XV": {"connects_to":["traps IV"],"requires":"|Basalt:6| and |Chalk:6|"},
"defy death XXXXVIII": {"connects_to":["melee weapon I"],"requires":"|Void:6|"},
"attack I": {"connects_to":["defense I"],"requires":"|Incense:9|"},
"knowledge XIII": {"connects_to":["uncategorized XVII","knowledge XXVI","macguffins IV"],"requires":"|Void:10|"},
"defy death XXXXIV": {"connects_to":["ranged weapon I"],"requires":"|Snow:5| and |Lilypad:5|"},
"vitality XI": {"connects_to":["goal XIV","attack III"],"requires":"|Rabbit Foot:9| and |Basalt:9|"},
"mana IV": {"connects_to":["link II"],"requires":"|Cinders:5|"},
"defy death XXXX": {"connects_to":["challenge IV"],"requires":"|Snow:4| and |Cinders:4|"},
"defy death XXXI": {"connects_to":["defy death XIX"],"requires":"|Rabbit Foot:12|"},
"price I": {"connects_to":["defense XIV","choice II"],"requires":"|Slate:5| and |Basalt:5|"},
"knowledge XXI": {"connects_to":["army II","stealth VII"],"requires":"|Chalk:5|"},
"goal XIV": {"connects_to":["amnesty IV","macguffins IX"],"requires":"|Incense:11|"},
"XP III": {"connects_to":["boss IX"],"requires":"|Snow:6| and |Strawberry:6|"},
"defy death XXVIII": {"connects_to":["second chance I","macguffins VI"],"requires":"|Slate:7| and |Incense:7|"},
"slots III": {"connects_to":["boss VIII"],"requires":"|Strawberry:12| and |Chalk:12|"},
"uncategorized XVII": {"connects_to":["defy death XXXVIII"],"requires":"|Spruce Branch:19| and |Lilypad:19|"},
"uncategorized X": {"requires":"|Clay:20|"},
"defy death V": {"connects_to":["XP IV"],"requires":"|Iron:7| and |Rabbit Foot:7|"},
"healing VIII": {"connects_to":["dangerous areas VII"],"requires":"|Basalt:10|"},
"XP XIV": {"connects_to":["link V"],"requires":"|Iron:9|"},
"second chance I": {"connects_to":["defy death XVIII","challenge III"],"requires":"|Snow:12|"},
"price X": {"connects_to":["defense XII"],"requires":"|Snow:13|"},
"defy death XIX": {"connects_to":["dangerous areas XI","time VI"],"requires":"|Limestone:12| and |Rabbit Foot:12|"},
"defy death XVII": {"connects_to":["god II"],"requires":"|Strawberry:7| and |Void:7|"},
"army II": {"connects_to":["refund II","goal VII"],"requires":"|Void:4| and |Eel:4|"},
"defy death XVIII": {"connects_to":["fragment II","explosion I"],"requires":"|Basalt:14| and |Void:14|"},
"goal VIII": {"connects_to":["knowledge V"],"requires":"|Snow:5| and |Slate:5|"},
"choice I": {"connects_to":["melee weapon VII"],"requires":"|Rabbit Foot:5|"},
"defy death XXXVIII": {"connects_to":["ranged weapon II"],"requires":"|Eel:21|"},
"knowledge VIII": {"connects_to":["attack II","defy death LI"],"requires":"|Strawberry:7|"},
"knowledge XX": {"connects_to":["speed II"],"requires":"|Void:7|"},
"utility V": {"connects_to":["fragment I"],"requires":"|Cinders:5| and |Strawberry:5|"},
"defy death XXVII": {"connects_to":["entrance rando III"],"requires":"|Snow:4| and |Void:4|"},
"uncategorized XIV": {"requires":"|Spruce Branch:10| and |Limestone:10|"},
"uncategorized XIX": {"connects_to":["XP VIII"],"requires":"|Basalt:9| and |Spruce Branch:9|"},
"knowledge XII": {"connects_to":["knowledge XXX","challenge X"],"requires":"|Snow:6|"},
"fragment III": {"connects_to":["choice III"],"requires":"|Spruce Branch:5|"},
"price XIV": {"connects_to":["XP XIII","refund V"],"requires":"|Chalk:7| and |Eel:7|"},
"logic II": {"requires":"|Snow:17|"},
"challenge III": {"connects_to":["key I","amnesty I"],"requires":"|Rabbit Foot:10| and |Spruce Branch:10| and |Incense:10|"},
"link III": {"requires":"|Stardust:10|"},
"knowledge XXX": {"connects_to":["defy death VII"],"requires":"|Lilypad:8|"},
"ice I": {"connects_to":["mana V"],"requires":"|Basalt:4|"},
"macguffins VII": {"requires":"|Void:12| and |Limestone:12|"},
"defense XIV": {"connects_to":["price XVII"],"requires":"|Spruce Branch:4| and |Slate:4|"},
"careful movement I": {"connects_to":["ranged weapon VI"],"requires":"|Rabbit Foot:10|"},
"fire II": {"connects_to":["melee weapon V","knowledge VII"],"requires":"|Spruce Branch:5|"},
"refund II": {"connects_to":["defense XVIII","price VI"],"requires":"|Lilypad:10|"},
"defy death XXXII": {"connects_to":["dangerous areas XII"],"requires":"|Slate:5| and |Eel:5|"},
"travel III": {"requires":"|Spruce Branch:4|"},
"mana I": {"requires":"|Lilypad:5| and |Basalt:5|"},
"amnesty III": {"connects_to":["sight II"],"requires":"|Iron:18|"},
"uncategorized XIII": {"connects_to":["XP VII","vitality IX"],"requires":"|Cinders:4| and |Incense:4|"},
"knowledge XIX": {"connects_to":["traps VI","defy death XXXXVII"],"requires":"|Slate:5|"},
"goal X": {"requires":"|Iron:14|"},
"dangerous areas II": {"connects_to":["explosion III"],"requires":"|Eel:3|"},
"dangerous areas XII": {"connects_to":["rest II"],"requires":"|Limestone:6|"},
"vitality XII": {"connects_to":["uncategorized IV"],"requires":"|Rabbit Foot:8| and |Limestone:8|"},
"healing VI": {"connects_to":["knowledge III"],"requires":"|Cinders:5| and |Incense:5|"},
"explosion IV": {"connects_to":["defy death IX","goal IX"],"requires":"|Incense:5| and |Slate:5|"},
"boss VIII": {"connects_to":["fire I"],"requires":"|Lilypad:6| and |Clay:6|"},
"defy death XIII": {"connects_to":["uncategorized VII"],"requires":"|Iron:8| and |Stardust:8|"},
"XP XIII": {"connects_to":["key IV"],"requires":"|Basalt:12|"},
"vitality I": {"connects_to":["link IV"],"requires":"|Void:5| and |Limestone:5|"},
"ranged weapon II": {"connects_to":["knowledge XV"],"requires":"|Incense:14| and |Iron:14| and |Limestone:14|"},
"melee weapon I": {"connects_to":["price XIII"],"requires":"|Clay:5| and |Spruce Branch:5|"},
"defy death XII": {"connects_to":["melee weapon III"],"requires":"|Rabbit Foot:5| and |Snow:5|"},
"attack VII": {"connects_to":["travel I","second chance VII"],"requires":"|Strawberry:12|"},
"price XVII": {"connects_to":["macguffins VIII","goal XVI"],"requires":"|Incense:8| and |Iron:8|"},
"ammo I": {"connects_to":["defy death LVII","vitality IV"],"requires":"|Eel:4|"},
"stealth VII": {"connects_to":["defy death XXV"],"requires":"|Snow:5| and |Incense:5|"},
"goal V": {"connects_to":["logic I"],"requires":"|Lilypad:10|"},
"macguffins I": {"connects_to":["defense XX"],"requires":"|Stardust:9| and |Basalt:9|"},
"uncategorized VII": {"connects_to":["knowledge XIV","defense XIII"],"requires":"|Eel:14| and |Snow:14| and |Iron:14|"},
"link II": {"connects_to":["dangerous areas IX"],"requires":"|Basalt:12|"},
"defense XVIII": {"connects_to":["goal XVII"],"requires":"|Strawberry:9|"},
"defy death XXXXIII": {"requires":"|Basalt:4| and |Eel:4|"},
"travel IV": {"connects_to":["amnesty V","goal XII"],"requires":"|Incense:5|"},
"melee weapon V": {"connects_to":["defy death XV"],"requires":"|Spruce Branch:14|"},
"god II": {"connects_to":["knowledge XVII"],"requires":"|Incense:5| and |Slate:5|"},
"defense IV": {"connects_to":["progression balancing II"],"requires":"|Spruce Branch:5| and |Lilypad:5|"},
"knowledge XIV": {"requires":"|Limestone:8| and |Lilypad:8|"},
"knowledge XXV": {"connects_to":["challenge IX"],"requires":"|Lilypad:4|"},
"attack II": {"connects_to":["starting III","defy death XXIII"],"requires":"|Stardust:8| and |Void:8|"},
"knowledge XXVI": {"connects_to":["boss I","defense VII","price VIII"],"requires":"|Void:8| and |Cinders:8|"},
"vitality XVI": {"requires":"|Incense:10| and |Clay:10|"},
"uncategorized V": {"requires":"|Stardust:7| and |Clay:7|"},
"defense I": {"connects_to":["knowledge IX"],"requires":"|Cinders:5|"},
"dangerous areas XI": {"connects_to":["defense X"],"requires":"|Snow:7| and |Iron:7|"},
"macguffins III": {"connects_to":["defy death IV"],"requires":"|Chalk:19|"},
"dangerous areas VIII": {"connects_to":["traps VIII"],"requires":"|Incense:7|"},
"traps VI": {"requires":"|Chalk:7| and |Stardust:7|"},
"defense XX": {"requires":"|Incense:5|"},
"knowledge XV": {"connects_to":["breath I","refund I","challenge V"],"requires":"|Stardust:10| and |Slate:10|"},
"macguffins VIII": {"requires":"|Incense:16| and |Rabbit Foot:16|"},
"price XIII": {"connects_to":["uncategorized III"],"requires":"|Basalt:6| and |Clay:6|"},
"melee weapon VII": {"connects_to":["defense XV"],"requires":"|Stardust:5| and |Chalk:5|"},
"starting III": {"connects_to":["second chance IX","knowledge IV"],"requires":"|Lilypad:10| and |Cinders:10|"},
"challenge IV": {"connects_to":["defy death XXIV"],"requires":"|Void:16|"},
"defy death XXXIII": {"requires":"|Limestone:6|"},
"XP VIII": {"connects_to":["beast I"],"requires":"|Slate:5| and |Snow:5|"},
"boss I": {"requires":"|Rabbit Foot:12| and |Incense:12|"},
"second chance IX": {"requires":"|Rabbit Foot:11|"},
"goal VII": {"requires":"|Iron:7| and |Stardust:7|"},
"knowledge XVIII": {"requires":"|Iron:5|"},
"link V": {"connects_to":["melee weapon XI"],"requires":"|Eel:7| and |Lilypad:7|"},
"starting I": {"connects_to":["traps XIV"],"requires":"|Snow:8|"},
"macguffins VI": {"requires":"|Stardust:16| and |Strawberry:16|"},
"second chance VIII": {"connects_to":["logic III","defy death XXXXI"],"requires":"|Incense:5|"},
"knowledge VII": {"requires":"|Eel:9|"},
"travel I": {"connects_to":["amnesty II"],"requires":"|Spruce Branch:4| and |Basalt:4|"},
"dangerous areas VII": {"connects_to":["utility VI"],"requires":"|Slate:10|"},
"starting II": {"connects_to":["defy death XXXIV"],"requires":"|Incense:4| and |Chalk:4|"},
"ranged weapon VI": {"connects_to":["fire III"],"requires":"|Basalt:16|"},
"healing II": {"connects_to":["traps V"],"requires":"|Lilypad:4| and |Stardust:4|"},
"traps XIV": {"connects_to":["ranged weapon VII","utility I"],"requires":"|Lilypad:10|"},
"defy death XXIII": {"connects_to":["progression balancing V"],"requires":"|Cinders:8| and |Spruce Branch:8|"},
"ranged weapon I": {"connects_to":["time IV"],"requires":"|Rabbit Foot:17|"},
"traps X": {"requires":"|Limestone:4| and |Snow:4|"},
"utility II": {"connects_to":["defense XIX"],"requires":"|Basalt:4|"},
"progression balancing III": {"requires":"|Basalt:17|"},
"boss IX": {"connects_to":["defense XI","enemy damage I"],"requires":"|Incense:8|"},
"rest II": {"connects_to":["defy death XXVI","healing VII"],"requires":"|Snow:4| and |Stardust:4|"},
"melee weapon III": {"connects_to":["boss III"],"requires":"|Iron:5| and |Lilypad:5|"},
"key I": {"requires":"|Strawberry:12| and |Snow:12| and |Rabbit Foot:12|"},
"sight II": {"requires":"|Incense:9|"},
"enemy damage II": {"connects_to":["time I"],"requires":"|Slate:5| and |Eel:5|"},
"ranged weapon VII": {"requires":"|Lilypad:12|"},
"traps V": {"connects_to":["food I"],"requires":"|Limestone:8| and |Cinders:8|"},
"progression balancing II": {"connects_to":["utility IV"],"requires":"|Chalk:20| and |Iron:20|"},
"XP II": {"requires":"|Stardust:10|"},
"slots IV": {"requires":"|Lilypad:7| and |Void:7|"},
"beast I": {"connects_to":["macguffins II"],"requires":"|Basalt:10| and |Slate:10|"},
"utility VI": {"connects_to":["uncategorized XVIII","defense XVI"],"requires":"|Iron:13|"},
"defy death XXXVII": {"connects_to":["defy death XXXXIX","defy death LIX"],"requires":"|Eel:4| and |Snow:4|"},
"second chance VII": {"requires":"|Eel:8|"},
"macguffins IV": {"requires":"|Void:21| and |Basalt:21|"},
"entrance rando III": {"requires":"|Clay:13|"},
"key IV": {"connects_to":["defense IX"],"requires":"|Basalt:12| and |Strawberry:12|"},
"defy death XXVI": {"requires":"|Rabbit Foot:7| and |Incense:7|"},
"knowledge II": {"requires":"|Void:4|"},
"healing IX": {"connects_to":["defense VIII"],"requires":"|Lilypad:4|"},
"defy death VI": {"connects_to":["XP IX"],"requires":"|Snow:6| and |Void:6|"},
"price XI": {"requires":"|Lilypad:14|"},
"fragment II": {"connects_to":["uncategorized VIII","defense XVII"],"requires":"|Chalk:13|"},
"defense VII": {"requires":"|Snow:15|"},
"utility I": {"requires":"|Limestone:6|"},
"defy death LVII": {"connects_to":["sight I","attack IX"],"requires":"|Limestone:4| and |Clay:4|"},
"logic III": {"requires":"|Eel:14|"},
"uncategorized VI": {"requires":"|Snow:12| and |Stardust:12|"},
"traps IV": {"connects_to":["attack IV"],"requires":"|Incense:17|"},
"choice III": {"connects_to":["defy death LVIII"],"requires":"|Stardust:6|"},
"goal XVII": {"requires":"|Iron:9| and |Limestone:9|"},
"defy death XV": {"requires":"|Slate:15|"},
"stealth I": {"requires":"|Lilypad:5|"},
"ranged weapon V": {"requires":"|Rabbit Foot:8|"},
"defy death XXXXIX": {"requires":"|Void:14|"},
"attack IV": {"connects_to":["revenge I","explosion V"],"requires":"|Strawberry:10| and |Iron:10|"},
"time I": {"requires":"|Iron:7| and |Chalk:7|"},
"water I": {"requires":"|Incense:4|"},
"price IX": {"connects_to":["speed VI"],"requires":"|Snow:7| and |Limestone:7|"},
"goal II": {"connects_to":["traps II"],"requires":"|Slate:6|"},
"challenge IX": {"connects_to":["slots II","dangerous areas IV"],"requires":"|Incense:14|"},
"defy death IX": {"connects_to":["knowledge XXII"],"requires":"|Lilypad:7| and |Rabbit Foot:7|"},
"traps VIII": {"requires":"|Chalk:15|"},
"fragment I": {"connects_to":["progression balancing I"],"requires":"|Clay:11|"},
"defy death LI": {"requires":"|Lilypad:7| and |Spruce Branch:7|"},
"amnesty IV": {"connects_to":["second chance V"],"requires":"|Incense:13| and |Strawberry:13|"},
"challenge I": {"requires":"|Basalt:8| and |Cinders:8|"},
"defense IX": {"requires":"|Incense:6| and |Eel:6|"},
"traps II": {"requires":"|Lilypad:10|"},
"uncategorized VIII": {"connects_to":["ranged weapon IV"],"requires":"|Basalt:23| and |Iron:23|"},
"amnesty V": {"requires":"|Clay:8| and |Void:8|"},
"XP IV": {"connects_to":["low HP I"],"requires":"|Eel:8| and |Chalk:8|"},
"defense XI": {"connects_to":["healing V","dangerous areas I"],"requires":"|Eel:9|"},
"defy death XXXXVII": {"requires":"|Snow:5| and |Void:5|"},
"melee weapon IX": {"requires":"|Void:11| and |Limestone:11|"},
"speed II": {"connects_to":["link I","defy death XXXV"],"requires":"|Snow:9| and |Void:9|"},
"goal IX": {"connects_to":["price VII"],"requires":"|Iron:6| and |Chalk:6|"},
"sight I": {"connects_to":["traps I"],"requires":"|Lilypad:5| and |Void:5|"},
"melee weapon VI": {"requires":"|Spruce Branch:13|"},
"defy death VII": {"requires":"|Rabbit Foot:13| and |Incense:13|"},
"attack III": {"connects_to":["vitality II"],"requires":"|Strawberry:12|"},
"goal XV": {"requires":"|Eel:8| and |Chalk:8|"},
"revenge I": {"connects_to":["dangerous areas X"],"requires":"|Stardust:4|"},
"attack IX": {"requires":"|Chalk:7| and |Cinders:7|"},
"uncategorized XVIII": {"connects_to":["vitality III"],"requires":"|Basalt:24| and |Chalk:24|"},
"defy death II": {"requires":"|Stardust:6| and |Incense:6|"},
"luck II": {"requires":"|Lilypad:8| and |Spruce Branch:8|"},
"vitality XV": {"connects_to":["defy death XXIX"],"requires":"|Iron:7| and |Chalk:7|"},
"refund V": {"requires":"|Iron:7| and |Void:7|"},
"goal XII": {"connects_to":["XP XII"],"requires":"|Snow:5| and |Cinders:5|"},
"fire III": {"requires":"|Iron:6|"},
"goal VI": {"requires":"|Void:4| and |Lilypad:4|"},
"stealth II": {"requires":"|Chalk:4| and |Iron:4|"},
"healing VII": {"requires":"|Lilypad:5| and |Slate:5|"},
"knowledge XXIV": {"requires":"|Snow:4|"},
"copy III": {"connects_to":["explosion II"],"requires":"|Slate:6| and |Basalt:6|"},
"utility IV": {"requires":"|Incense:7| and |Snow:7|"},
"vitality II": {"requires":"|Strawberry:20|"},
"uncategorized III": {"requires":"|Eel:10| and |Lilypad:10|"},
"uncategorized XVI": {"requires":"|Spruce Branch:12| and |Limestone:12|"},
"logic I": {"requires":"|Strawberry:12| and |Lilypad:12|"},
"defy death XXXXII": {"requires":"|Clay:15|"},
"knowledge XVII": {"connects_to":["electricity I"],"requires":"|Rabbit Foot:7| and |Cinders:7|"},
"explosion II": {"requires":"|Spruce Branch:6| and |Incense:6|"},
"progression balancing V": {"requires":"|Limestone:21| and |Lilypad:21|"},
"defense XII": {"connects_to":["army IV"],"requires":"|Incense:5| and |Snow:5|"},
"attack VIII": {"requires":"|Rabbit Foot:5| and |Basalt:5|"},
"challenge II": {"requires":"|Iron:9|"},
"defense XIII": {"requires":"|Basalt:9| and |Limestone:9|"},
"knowledge IX": {"requires":"|Lilypad:6|"},
"defense XVII": {"connects_to":["defy death X"],"requires":"|Clay:17|"},
"second chance IV": {"requires":"|Eel:6| and |Void:6|"},
"defense X": {"connects_to":["breath II"],"requires":"|Basalt:7| and |Incense:7|"},
"vitality III": {"requires":"|Strawberry:24| and |Chalk:24|"},
"defense VIII": {"requires":"|Chalk:4|"},
"amnesty I": {"requires":"|Strawberry:14| and |Void:14| and |Stardust:14|"},
"defy death XXXIV": {"connects_to":["defy death LII"],"requires":"|Iron:6|"},
"breath II": {"requires":"|Eel:9|"},
"price VIII": {"requires":"|Spruce Branch:10| and |Limestone:10| and |Rabbit Foot:10|"},
"slots I": {"requires":"|Limestone:9| and |Chalk:9|"},
"defy death XXXXI": {"requires":"|Strawberry:13|"},
"traps I": {"requires":"|Clay:8| and |Strawberry:8|"},
"breath I": {"connects_to":["rest I"],"requires":"|Slate:17|"},
"defy death XI": {"requires":"|Rabbit Foot:4| and |Stardust:4|"},
"link IV": {"requires":"|Cinders:6|"},
"macguffins II": {"requires":"|Iron:16| and |Eel:16|"},
"copy II": {"requires":"|Cinders:5|"},
"army III": {"connects_to":["copy I"],"requires":"|Strawberry:6|"},
"defy death LVIII": {"connects_to":["defy death XXI"],"requires":"|Slate:6| and |Stardust:6|"},
"healing V": {"requires":"|Eel:10|"},
"defy death XXXIX": {"requires":"|Rabbit Foot:4| and |Strawberry:4|"},
"army I": {"requires":"|Stardust:3|"},
"time II": {"requires":"|Lilypad:4| and |Void:4|"},
"price XVI": {"connects_to":["XP I"],"requires":"|Eel:13|"},
"entrance rando I": {"requires":"|Basalt:10|"},
"time IV": {"connects_to":["defense II"],"requires":"|Spruce Branch:14|"},
"fire I": {"connects_to":["melee weapon IV"],"requires":"|Limestone:4| and |Slate:4|"},
"speed VI": {"requires":"|Chalk:12| and |Iron:12|"},
"dangerous areas III": {"connects_to":["defy death XXXXV"],"requires":"|Stardust:4| and |Slate:4|"},
"second chance V": {"requires":"|Limestone:12|"},
"explosion III": {"requires":"|Eel:4|"},
"ranged weapon IV": {"requires":"|Eel:19| and |Clay:19|"},
"link I": {"requires":"|Iron:17|"},
"army IV": {"requires":"|Stardust:11|"},
"defy death LII": {"requires":"|Rabbit Foot:8| and |Void:8|"},
"electricity I": {"requires":"|Incense:15|"},
"defy death XXV": {"requires":"|Eel:7| and |Cinders:7|"},
"XP VII": {"requires":"|Stardust:4|"},
"defy death XXXV": {"requires":"|Limestone:9| and |Chalk:9|"},
"explosion I": {"requires":"|Stardust:8| and |Spruce Branch:8|"},
"knowledge XXII": {"connects_to":["robot I"],"requires":"|Iron:5| and |Stardust:5|"},
"defy death XXI": {"requires":"|Strawberry:12|"},
"choice IV": {"connects_to":["entrance rando II"],"requires":"|Void:5|"},
"dangerous areas I": {"requires":"|Basalt:6| and |Snow:6|"},
"food I": {"requires":"|Stardust:6| and |Limestone:6|"},
"slots II": {"requires":"|Rabbit Foot:10| and |Basalt:10|"},
"robot I": {"requires":"|Void:4|"},
"price VII": {"requires":"|Basalt:9| and |Iron:9|"},
"defy death LIX": {"requires":"|Chalk:4| and |Snow:4|"},
"XP IX": {"requires":"|Limestone:5| and |Cinders:5|"},
"low HP I": {"connects_to":["defy death LIII"],"requires":"|Clay:4|"},
"uncategorized IV": {"requires":"|Rabbit Foot:11| and |Eel:11|"},
"defense XVI": {"requires":"|Slate:14|"},
"defense XV": {"connects_to":["defy death III"],"requires":"|Eel:4| and |Chalk:4|"},
"entrance rando II": {"connects_to":["traps IX"],"requires":"|Stardust:11|"},
"uncategorized XII": {"requires":"|Void:11| and |Slate:11| and |Eel:11|"},
"XP XII": {"requires":"|Basalt:6| and |Stardust:6|"},
"knowledge V": {"requires":"|Iron:4| and |Limestone:4|"},
"knowledge III": {"requires":"|Snow:9|"},
"time VI": {"requires":"|Iron:13|"},
"goal XVI": {"requires":"|Void:8| and |Strawberry:8|"},
"defense III": {"requires":"|Chalk:5|"},
"price VI": {"requires":"|Lilypad:8| and |Iron:8|"},
"defy death XXXXV": {"requires":"|Iron:6| and |Limestone:6|"},
"vitality IX": {"requires":"|Void:8|"},
"mana VI": {"connects_to":["stealth VI"],"requires":"|Eel:6|"},
"defy death III": {"requires":"|Void:10| and |Slate:10| and |Basalt:10|"},
"vitality IV": {"requires":"|Stardust:7| and |Incense:7|"},
"mana III": {"requires":"|Rabbit Foot:5|"},
"careful movement IV": {"requires":"|Clay:7| and |Incense:7|"},
"refund I": {"requires":"|Strawberry:14| and |Iron:14| and |Cinders:14|"},
"challenge X": {"requires":"|Cinders:12| and |Limestone:12|"},
"defy death X": {"requires":"|Slate:15| and |Limestone:15|"},
"melee weapon XI": {"requires":"|Lilypad:9| and |Clay:9|"},
"defy death XXIX": {"requires":"|Strawberry:5| and |Chalk:5|"},
"defense XIX": {"requires":"|Incense:5|"},
"explosion V": {"requires":"|Void:8| and |Chalk:8|"},
"stealth VI": {"requires":"|Eel:4| and |Clay:4|"},
"dangerous areas X": {"requires":"|Snow:7| and |Incense:7|"},
"defy death XXIV": {"requires":"|Clay:11|"},
"enemy damage I": {"requires":"|Chalk:7| and |Incense:7|"},
"defy death XXX": {"requires":"|Lilypad:12|"},
"XP I": {"requires":"|Eel:8| and |Cinders:8|"},
"knowledge IV": {"requires":"|Eel:7| and |Rabbit Foot:7|"},
"choice II": {"requires":"|Cinders:4| and |Stardust:4|"},
"traps IX": {"requires":"|Incense:10| and |Iron:10|"},
"macguffins IX": {"requires":"|Strawberry:15| and |Slate:15|"},
"defy death LV": {"requires":"|Stardust:10|"},
"boss III": {"requires":"|Void:5| and |Incense:5|"},
"knowledge XXIX": {"requires":"|Incense:4| and |Basalt:4|"},
"amnesty II": {"requires":"|Void:12| and |Lilypad:12|"},
"dangerous areas IV": {"requires":"|Clay:5|"},
"defy death IV": {"requires":"|Limestone:11|"},
"mana V": {"requires":"|Void:5|"},
"dangerous areas IX": {"requires":"|Spruce Branch:6|"},
"defy death LIII": {"requires":"|Strawberry:8| and |Stardust:8|"},
"progression balancing I": {"requires":"|Clay:22| and |Limestone:22|"},
"melee weapon IV": {"requires":"|Rabbit Foot:10| and |Eel:10|"},
"copy I": {"requires":"|Void:5| and |Rabbit Foot:5|"},
"XP XI": {"requires":"|Limestone:4| and |Slate:4|"},
"defense II": {"requires":"|Lilypad:5| and |Incense:5|"},
"rest I": {"connects_to":["uncategorized XX"],"requires":"|Iron:14| and |Lilypad:14|"},
"uncategorized XX": {"requires":"|Cinders:40| and |Clay:40| and |Rabbit Foot:40|"},
"challenge V": {"requires":"|Cinders:22| and |Snow:22| and |Slate:22|"}}